multiply_bootleg_dev/__init__.py
multiply_bootleg_dev/multiplication.py
multiply_bootleg_dev-0.1.1.dist-info/METADATA
multiply_bootleg_dev-0.1.1.dist-info/WHEEL
multiply_bootleg_dev-0.1.1.dist-info/top_level.txt
multiply_bootleg_dev-0.1.1.dist-info/RECORD
